setup.py
bin/Grouper
biogrouper.egg-info/PKG-INFO
biogrouper.egg-info/SOURCES.txt
biogrouper.egg-info/dependency_links.txt
biogrouper.egg-info/not-zip-safe
biogrouper.egg-info/requires.txt
biogrouper.egg-info/top_level.txt
grouper/__init__.py
grouper/eqnet.py
grouper/filtGraph.py
grouper/iterLabel.py
grouper/processLabels.py