Metadata-Version: 1.0
Name: biogrouper
Version: 0.1.4
Summary: Graph-based clustering and annotation for improved de novo transcriptome analysis
Home-page: https://github.com/COMBINE-lab/Grouper
Author: Laraib Malik, Fatemeh Almodaresi, Rob Patro
Author-email: rob.patro@cs.stonybrook.edu
License: BSD with attribution
Platform: UNKNOWN
